Workbook

Sheet Summary
A1: Investigator scoring of extraction run 20260921T180242 (157 drafts, gpt-oss-120b, prompt v1)
A2: Legend: column K (investigator decision) and columns L-M are Claude's proposed decisions for a named reviewer to accept or overrule in the review workbook; columns A-I are the run's own output.
A3: decision | B3: count | C3: share | D3: meaning
A4: COMPILE_NOW | B4: =COUNTIF('Scored drafts'!$L$2:$L$158,A4) -> 6 | C4: =B4/$B$10 -> 0.038216561 | D4: Approve. Compiles to a detector with today's grammar.
A5: LEAD | B5: =COUNTIF('Scored drafts'!$L$2:$L$158,A5) -> 57 | C5: =B5/$B$10 -> 0.36305732 | D5: Approve as reviewed lead. True rule; becomes a detector after the named Phase-2 item (population conditions, code-range/category resolver, modifier/provider-type/POS compilers, amounts).
A6: FIX | B6: =COUNTIF('Scored drafts'!$L$2:$L$158,A6) -> 25 | C6: =B6/$B$10 -> 0.15923567 | D6: Statement or quote must be corrected before a decision - mostly the grounding attached the wrong sentence; a few statements add or drop a condition.
A7: KNOWLEDGE | B7: =COUNTIF('Scored drafts'!$L$2:$L$158,A7) -> 53 | C7: =B7/$B$10 -> 0.33757962 | D7: True policy, not checkable from a paid claim line. Keep in the KB (not_checkable); never a detector.
A8: DUP_OF_SEED | B8: =COUNTIF('Scored drafts'!$L$2:$L$158,A8) -> 8 | C8: =B8/$B$10 -> 0.050955414 | D8: Already in state_rules as a migrated seed. Reject the draft; canonical-key fix pending.
A9: REJECT | B9: =COUNTIF('Scored drafts'!$L$2:$L$158,A9) -> 8 | C9: =B9/$B$10 -> 0.050955414 | D9: Drop: exact duplicate, stale (ICD-9), regex noise, invented numbers, or quote unrelated to statement.
A10: total | B10: =SUM(B4:B9) -> 157 | C10: =SUM(C4:C9) -> 1
A12: quote supports statement? | B12: count
A13: yes | B13: =COUNTIF('Scored drafts'!$J$2:$J$158,A13) -> 134
A14: PARTIAL | B14: =COUNTIF('Scored drafts'!$J$2:$J$158,A14) -> 5
A15: NO | B15: =COUNTIF('Scored drafts'!$J$2:$J$158,A15) -> 18
A17: found by | B17: count
A18: model | B18: =COUNTIF('Scored drafts'!$I$2:$I$158,A18) -> 149
A19: pattern+model | B19: =COUNTIF('Scored drafts'!$I$2:$I$158,A19) -> 6
A20: pattern | B20: =COUNTIF('Scored drafts'!$I$2:$I$158,A20) -> 2
A22: Findings that change the pipeline
A23: 1. Grounding attaches the wrong sentence in ~20 drafts (all at confidence 0.9-1.0). When the model's quote is not found verbatim, the fuzzy matcher substitutes the best-overlapping sentence; the drift check is too weak. Fix: require the statement's numbers/codes to appear in the matched sentence, otherwise DROP - never substitute.
A24: 2. Model confidence is uninformative: misgrounded and invented rows sit at 0.97-1.0. Do not sort the review by it.
A25: 3. The regex layer adds only noise now (2 pattern-only drafts, both junk). Keep it as a cross-check flag, stop emitting pattern-only drafts.
A26: 4. Same rule extracted twice (rows 36/37, 42/52) and 8 drafts duplicate migrated seeds - the key hashes the whole predicate dict. Canonicalise the key.
A27: 5. 6 of 157 compile today. ~57 more compile after Phase 2: member conditions (age/program), code-range + category->code resolver ('per diem codes', 'E/M codes', 'DME'), and the modifier_required / provider_type / place_of_service compilers. That is the actual Phase-2 priority list, in that order.
A28: 6. Three in-chapter conflicts the model surfaced (77 vs 112 VFC admin codes; 118 vs 137 foot care by effective date; 114 vs 120 diabetes education). Reviewer decides; effective_date support needed for 118/137.
A30: fidelity (one label per row, non-overlapping) | B30: count
A31: faithful | B31: =COUNTIF('Scored drafts'!$K$2:$K$158,A31) -> 116
A32: faithful - in-chapter conflict | B32: =COUNTIF('Scored drafts'!$K$2:$K$158,A32) -> 4
A33: faithful - unit basis unclear | B33: =COUNTIF('Scored drafts'!$K$2:$K$158,A33) -> 1
A34: wrong quote attached | B34: =COUNTIF('Scored drafts'!$K$2:$K$158,A34) -> 16
A35: statement adds/drops a condition | B35: =COUNTIF('Scored drafts'!$K$2:$K$158,A35) -> 7
A36: duplicate of seed | B36: =COUNTIF('Scored drafts'!$K$2:$K$158,A36) -> 8
A37: duplicate draft | B37: =COUNTIF('Scored drafts'!$K$2:$K$158,A37) -> 2
A38: regex noise | B38: =COUNTIF('Scored drafts'!$K$2:$K$158,A38) -> 2
A39: stale (ICD-9) | B39: =COUNTIF('Scored drafts'!$K$2:$K$158,A39) -> 1
A40: total | B40: =SUM(B31:B39) -> 157

Sheet Scored drafts
A1: row | B1: rule_id | C1: chapter | D1: section | E1: statement (proposed_rule) | F1: verbatim_quote | G1: model confidence | H1: population | I1: found by | J1: quote supports statement? | K1: fidelity (one label per row) | L1: investigator decision | M1: blocker / reason | N1: note
A2: 3 | B2: EXT-de1dcb76d419bb54 | C2: 10 | D2: SUPPLIES, MATERIALS, INJECTABLE DRUGS | E2: AHCCCS does not reimburse providers on a fee-for-service basis for services billed using procedure code 99070. | F2: AHCCCS does not reimburse providers on a fee-for-service basis for services billed using procedure code 99070 (Supplies and materials, except spectacles, provided by the physician over and above those usually included with the office visit or other services rendered). | G2: 1 | H2: all | I2: model | J2: yes | K2: faithful | L2: COMPILE_NOW | M2: code_not_covered | N2: 99070 paid on FFS = finding. Row 155 is the regex misreading 'except spectacles' inside the code description - reject that one.
A3: 10 | B3: EXT-80b8a1033e6a92a7 | C3: 10 | D3: ANESTHESIA MEDICAL DIRECTION | E3: The anesthesia service with CPT code 00938 (Insertion of penile prosthesis) is not covered. | F3: The following anesthesia services are not covered: • 00938 (Insertion of penile prosthesis) | G3: 1 | H3: all | I3: model | J3: yes | K3: faithful | L3: COMPILE_NOW | M3: code_not_covered | N3: 00938 anesthesia not covered.
A4: 38 | B4: EXT-3bda3d647af1039a | C4: 10 | D4: MULTI-SPECIALTY INTERDISCIPLINARY CLINIC | E4: T1015 (MSIC Service Coordination Payment) may be billed only once per day per MSIC. | F4: MSIC-eligible visits may be billed with a T1015 procedure code once per day, per MSIC. Multiple visits on the same day by a single MSIC are eligible for only one T1015 code payment. | G4: 0.99 | H4: all | I4: model | J4: yes | K4: faithful | L4: COMPILE_NOW | M4: max_units_per_dos | N4: T1015 once per day PER MSIC -> scope member_provider_day (per_dos), not member_day.
A5: 55 | B5: EXT-66855c812580f096 | C5: 10 | D5: FAMILY PLANNING SERVICES | E5: 11975 is not a covered/reimbursable service. | F5: Do not bill for CPT codes: • 11975 - Insertion, implantable contraceptive capsules; and • 11977 - Removal with reinsertion, implantable contraceptive capsules. | G5: 0.98 | H5: all | I5: pattern+model | J5: yes | K5: faithful | L5: COMPILE_NOW | M5: code_not_covered | N5: 'Do not bill' 11975.
A6: 57 | B6: EXT-67b7f6b914f4f3b9 | C6: 10 | D6: FAMILY PLANNING SERVICES | E6: 11977 is not a covered/reimbursable service. | F6: Do not bill for CPT codes: • 11975 - Insertion, implantable contraceptive capsules; and • 11977 - Removal with reinsertion, implantable contraceptive capsules. | G6: 0.98 | H6: all | I6: pattern+model | J6: yes | K6: faithful | L6: COMPILE_NOW | M6: code_not_covered | N6: 'Do not bill' 11977.
A7: 54 | B7: EXT-05527bb75a006e15 | C7: 19 | D7: MEDICATION | E7: The billing unit for H0020 is one dose per day. | F7: The billing unit is one dose per day (includes cost associated with drug and administration). | G7: 0.98 | H7: all | I7: model | J7: yes | K7: faithful | L7: COMPILE_NOW | M7: max_units_per_day | N7: H0020 = 1 dose/day per member.
A8: 1 | B8: EXT-2fcd139f3b5ceeed | C8: 10 | D8: REHABILITATIVE SERVICES DOCUMENTATION REQUIREMENTS | E8: Outpatient rehabilitation services are NOT covered for FES members. | F8: Outpatient rehabilitation services are NOT covered for FES members. | G8: 1 | H8: FES members | I8: model | J8: yes | K8: faithful | L8: LEAD | M8: population + code_resolution | N8: Outpatient rehab not covered for FES members.
A9: 4 | B9: EXT-659523331607f688 | C9: 10 | D9: SURGEON BILLING | E9: Multiple surgical procedures performed on the same member on the same day must be billed using modifier 51. | F9: Multiple surgical procedures performed on the same member on the same day must be billed using modifier 51. | G9: 1 | H9: all | I9: model | J9: yes | K9: faithful | L9: LEAD | M9: code_range + modifier | N9: 2+ surgical codes same day same provider without modifier 51.
A10: 5 | B10: EXT-63be4f68b288063c | C10: 10 | D10: SURGEON BILLING | E10: Each secondary surgical procedure is reimbursed at 50 percent of the capped fee or billed charges, whichever is less. | F10: Each secondary surgical procedure is reimbursed at 50 percent of the capped fee or billed charges, whichever is less. | G10: 1 | H10: all | I10: model | J10: yes | K10: faithful | L10: LEAD | M10: pricing | N10: Secondary surgery paid at 50% - Phase 3 price audit.
A11: 34 | B11: EXT-393137d66a09561e | C11: 10 | D11: TELEHEALTH | E11: Tele presenter services are not billable. | F11: Tele presenter services are not billable. | G11: 0.99 | H11: all | I11: model | J11: yes | K11: faithful | L11: LEAD | M11: code_resolution | N11: Tele-presenter not billable - which code (T1014?) is not stated.
A12: 35 | B12: EXT-470b9d6d80193812 | C12: 10 | D12: NATUROPATHIC PHYSICIANS | E12: Naturopathic physician services are not covered for AHCCCS members 21 years of age and older. | F12: NOTE: Naturopathic physician services are not covered for AHCCCS members 21 years of age and older. | G12: 0.99 | H12: all | I12: model | J12: yes | K12: faithful | L12: LEAD | M12: population + provider_type | N12: Naturopathic services not covered 21+.
A13: 58 | B13: EXT-ecd82a178d8a55a5 | C13: 10 | D13: CORRECT CODING INITIATIVE | E13: Modifier 59 cannot be billed with evaluation and management codes (99201-99499) or radiation therapy codes (77261-77499). | F13: Modifier 59 cannot be billed with evaluation and management codes (99201-99499) or radiation therapy codes (77261-77499). | G13: 0.98 | H13: all | I13: pattern+model | J13: yes | K13: faithful | L13: LEAD | M13: code_range + modifier predicate | N13: Modifier 59 on E/M 99201-99499 or radiation 77261-77499 = finding. Classic FWA edit; needs range support and a modifier_prohibited predicate. High value.
... A158: 144 | B158: EXT-f7d59aaa7940b7a9 | C158: 19 | D158: CODING & COMMON MODIFIERS FOR BILLING BEHAVIORAL HEALTH SERVICES | E158: HQ modifier(s) must be used for non-IOP services when services are delivered in a group setting. | F158: Inpatient per diem BH codes are priced to include all the non-professional BH services the member will receive in a day. Additional BH services shall not be unbundled from the per diem code. | G158: 0.93 | H158: all | I158: model | J158: NO | K158: wrong quote attached | L158: REJECT | M158: misgrounded | N158: Quote (per diem unbundling) has nothing to do with the statement (HQ for non-IOP). Statement is also circular (group = HQ).
